{
    "language":"grc",
    "englishTitle":"Hymn 28 to Athena",
    "original-urn":"urn:cts:greekLit:tlg0013.tlg028.perseus-grc2",
    "author":"homeric hymns",
    "urn":"urn:cts:greekLit:tlg0013.tlg028.perseus-grc2-simple",
    "text":{
        "0":"Παλλάδ᾽ Ἀθηναίην, κυδρὴν θεόν, ἄρχομ᾽ ἀείδειν ",
        "1":"γλαυκῶπιν, πολύμητιν, ἀμείλιχον ἦτορ ἔχουσαν, ",
        "2":"παρθένον αἰδοίην, ἐρυσίπτολιν, ἀλκήεσσαν, ",
        "3":"Τριτογενῆ, τὴν αὐτὸς ἐγείνατο μητίετα Ζεὺς ",
        "4":"σεμνῆς ἐκ κεφαλῆς, πολεμήια τεύχε᾽ ἔχουσαν, ",
        "5":"χρύσεα, παμφανόωντα: σέβας δ᾽ ἔχε πάντας ὁρῶντας ",
        "6":"ἀθανάτους: ἣ δὲ πρόσθεν Διὸς αἰγιόχοιο ",
        "7":"ἐσσυμένως ὤρουσεν ἀπ᾽ ἀθανάτοιο καρήνου, ",
        "8":"σείσασ᾽ ὀξὺν ἄκοντα: μέγας δ᾽ ἐλελίζετ᾽ Ὄλυμπος ",
        "9":"δεινὸν ὑπὸ βρίμης γλαυκώπιδος: ἀμφὶ δὲ γαῖα ",
        "10":"σμερδαλέον ἰάχησεν: ἐκινήθη δ᾽ ἄρα πόντος, ",
        "11":"κύμασι πορφυρέοισι κυκώμενος: ἔκχυτο δ᾽ ἅλμη ",
        "12":"ἐξαπίνης: στῆσεν δ᾽ Ὑπερίονος ἀγλαὸς υἱὸς ",
        "13":"ἵππους ὠκύποδας δηρὸν χρόνον, εἰσότε κούρη ",
        "14":"εἵλετ᾽ ἀπ᾽ ἀθανάτων ὤμων θεοείκελα τεύχη ",
        "15":"Παλλὰς Ἀθηναίη: γήθησε δὲ μητίετα Ζεύς. ",
        "16":"καὶ σὺ μὲν οὕτω χαῖρε, Διὸς τέκος αἰγιόχοιο: ",
        "17":"αὐτὰρ ἐγὼ καὶ σεῖο καὶ ἄλλης μνήσομ᾽ ἀοιδῆς."
    },
    "source":"Perseus Digital Library",
    "originalTitle":"Hymn 28 to Athena",
    "edition":"Hymni Homerici, creator; Hesiod, creator; Homer, creator; Evelyn-White, Hugh G. (Hugh Gerard), d. 1924, translator",
    "sourceLink":"http://www.perseus.tufts.edu/hopper/",
    "meta":"line"
}